pulumi_automation_utils/__init__.py
pulumi_automation_utils/certs_and_keys.py
pulumi_automation_utils/common.py
pulumi_automation_utils/environment.py
pulumi_automation_utils/login_config.py
pulumi_automation_utils/pulumi_config.py
pulumi_automation_utils-1.3.0.dist-info/LICENSE
pulumi_automation_utils-1.3.0.dist-info/METADATA
pulumi_automation_utils-1.3.0.dist-info/WHEEL
pulumi_automation_utils-1.3.0.dist-info/top_level.txt
pulumi_automation_utils-1.3.0.dist-info/RECORD
