Metadata-Version: 2.1
Name: pulumi-automation-utils
Version: 1.3.0
Summary: Package contains functions and classes that can be utilized in the automation of pulumi python deployments
Author-email: Adam Cubel <adam.cubel@tactware.net>
Project-URL: Homepage, https://github.com/adamcubel/pulumi-automation-utils
Project-URL: Bug Tracker, https://github.com/adamcubel/pulumi-automation-utils/issues
Classifier: Programming Language :: Python :: 3
Classifier: License :: OSI Approved :: MIT License
Classifier: Operating System :: OS Independent
Requires-Python: >=3.7
License-File: LICENSE
